pyvmrun/__init__.py
pyvmrun/__main__.py
pyvmrun/pyvmrun.py
pyvmrun-0.2.1.dist-info/LICENSE
pyvmrun-0.2.1.dist-info/METADATA
pyvmrun-0.2.1.dist-info/WHEEL
pyvmrun-0.2.1.dist-info/top_level.txt
pyvmrun-0.2.1.dist-info/RECORD
