Metadata-Version: 2.1
Name: pyvmrun
Version: 0.2.1
Summary: Platform-independent VMWare/vmrun control from Python
Home-page: https://github.com/bpengu1n/pyvmrun
Author: BPengu1n
Author-email: bpengu1n+pypi@penguin-sec.org
License: UNKNOWN
Project-URL: Bug Tracker, https://github.com/bpengu1n/pyvmrun/issues
Platform: UNKNOWN
Classifier: Programming Language :: Python :: 3
Classifier: License :: OSI Approved :: GNU General Public License v3 or later (GPLv3+)
Classifier: Operating System :: OS Independent
Classifier: Development Status :: 5 - Production/Stable
Classifier: Topic :: Software Development :: Libraries :: Python Modules
Requires-Python: >=3.6
